api_tests/__init__.py
api_tests/test.py
api_tests/private/__init__.py
api_tests/private/accounts.py
api_tests/private/apiutils.py
api_tests/private/client.py
api_tests/private/collections.py
api_tests/private/common.py
api_tests/private/compatpatch.py
api_tests/private/discover.py
api_tests/private/feed.py
api_tests/private/friendships.py
api_tests/private/highlights.py
api_tests/private/igtv.py
api_tests/private/live.py
api_tests/private/locations.py
api_tests/private/media.py
api_tests/private/misc.py
api_tests/private/tags.py
api_tests/private/upload.py
api_tests/private/users.py
api_tests/private/usertags.py
instapi/__init__.py
instapi/client.py
instapi/compat.py
instapi/compatpatch.py
instapi/constants.py
instapi/errors.py
instapi/http.py
instapi/utils.py
instapi/version.txt
instapi/endpoints/__init__.py
instapi/endpoints/accounts.py
instapi/endpoints/addressbook.py
instapi/endpoints/collections.py
instapi/endpoints/common.py
instapi/endpoints/discover.py
instapi/endpoints/feed.py
instapi/endpoints/friendships.py
instapi/endpoints/highlights.py
instapi/endpoints/igtv.py
instapi/endpoints/insights.py
instapi/endpoints/live.py
instapi/endpoints/locations.py
instapi/endpoints/media.py
instapi/endpoints/misc.py
instapi/endpoints/tags.py
instapi/endpoints/upload.py
instapi/endpoints/users.py
instapi/endpoints/usertags.py
instapi-0.1.4.dist-info/LICENSE
instapi-0.1.4.dist-info/METADATA
instapi-0.1.4.dist-info/WHEEL
instapi-0.1.4.dist-info/top_level.txt
instapi-0.1.4.dist-info/RECORD
