Metadata-Version: 2.1
Name: instapi
Version: 0.1.4
Summary: A client interface for the private Instagram API.
Home-page: https://github.com/breuerfelix/instapi
Author: Felix Breuer
Author-email: hi@felixbreuer.me
License: MIT
Keywords: instagram private api
Platform: UNKNOWN
Classifier: Development Status :: 4 - Beta
Classifier: Intended Audience :: Developers
Classifier: License :: OSI Approved :: MIT License
Classifier: Topic :: Software Development :: Libraries :: Python Modules
Classifier: Programming Language :: Python :: 3
Requires-Python: >=3
